Metadata-Version: 2.1
Name: stuoe-extensions
Version: 0.0.1
Summary: Stuoe Extensions
Home-page: https://stuoe.cn
Author: snbck
Author-email: snbckcode@gmail.com
License: Apache License
Platform: UNKNOWN
